README.rst
setup.cfg
setup.py
chainload/__init__.py
chainload/chainload.py
chainload.egg-info/PKG-INFO
chainload.egg-info/SOURCES.txt
chainload.egg-info/dependency_links.txt
chainload.egg-info/requires.txt
chainload.egg-info/top_level.txt