Metadata-Version: 1.1
Name: chainload
Version: 1.4
Summary: Load a value from an environmental variable, YAML/JSON file, or default to a provided value.
Home-page: http://github.com/tristanfisher/chainload
Author: Tristan Fisher
Author-email: code@tristanfisher.com
License: Apache 2.0
Platform: UNKNOWN
Classifier: Environment :: MacOS X
Classifier: Intended Audience :: Developers
Classifier: License :: OSI Approved :: Apache Software License
Classifier: Operating System :: MacOS
Classifier: Operating System :: Unix
Classifier: Programming Language :: Python
Classifier: Programming Language :: Python :: 2
Classifier: Programming Language :: Python :: 2.7
Classifier: Programming Language :: Python :: 3
Classifier: Programming Language :: Python :: 3.4
Classifier: Topic :: Utilities
